roll.py
xdice.py
xdice-1.2.1.dist-info/LICENSE.txt
xdice-1.2.1.dist-info/METADATA
xdice-1.2.1.dist-info/WHEEL
xdice-1.2.1.dist-info/top_level.txt
xdice-1.2.1.dist-info/RECORD
