Metadata-Version: 2.1
Name: xdice
Version: 1.2.1
Summary: The swiss knife for Dice roll : Command line, API (documented!), advanced dice notation parser, compilable patterns...etc.
Home-page: https://github.com/cro-ki/xdice
Author: Olivier Massot
Author-email: croki.contact@gmail.com
License: GNU
Keywords: xdice roll d20 game random parser dices role board
Platform: UNKNOWN
Classifier: Development Status :: 5 - Production/Stable
Classifier: Intended Audience :: Developers
Classifier: Intended Audience :: Other Audience
Classifier: Topic :: Games/Entertainment :: Board Games
Classifier: Topic :: Games/Entertainment :: Role-Playing
Classifier: Topic :: Games/Entertainment :: Multi-User Dungeons (MUD)
Classifier: Topic :: Games/Entertainment :: Turn Based Strategy
Classifier: License :: OSI Approved :: GNU General Public License (GPL)
Classifier: Programming Language :: Python :: 3.4
Classifier: Programming Language :: Python :: 3.5
Classifier: Programming Language :: Python :: 3.6
Classifier: Programming Language :: Python :: 3.7
Classifier: Programming Language :: Python :: 3.8
Requires-Python: >=3.4
